{
  "id": "20260628084341-ubqr",
  "topic": "성수기 CS 준비하려고 하는데, 인력 공백이 매출 손실로 이어지는 이유",
  "createdAt": "2026-06-28T08:43:41.841Z",
  "channels": {
    "instagram": "{\n  \"planning\": \"성수기 고객 문의 폭증으로 인한 인력 공백은 단순한 CS 문제가 아닌, 고객 이탈과 직접적인 매출 손실로 이어지는 운영상 단절이다. 고정적인 인력 운영의 한계를 분석하고, 인력 공백이 만드는 매출 손실 시그널을 제시한 뒤, 유연하고 전문적인 CS 운영으로 성수기를 기회로 만드는 관점을 제시한다.\",\n  \"content_title\": \"성수기 CS 인력 공백, 매출 손실 막는 유연한 운영 전략\",\n  \"cards\": [\n    {\n      \"card_no\": 1,\n      \"card_type\": \"후킹 카드\",\n      \"template_name\": \"Instagram post - first\",\n      \"layout_type\": \"cover\",\n      \"cloud_label\": \"Insight\",\n      \"series_title\": \"\",\n      \"title\": \"성수기, CS 인력\\n갑자기 늘릴 수 있나요?\",\n      \"highlight_text\": \"\",\n      \"subtitle\": \"공백은 곧 매출 손실로 이어집니다\",\n      \"body\": \"성수기 CS 인력 공백이 단순한 문제가 아닌, 매출 손실로 이어지는 악순환의 시작일 수 있다는 점을 환기합니다.\",\n      \"items\": [],\n      \"cta\": \"\",\n      \"design_point\": \"\"\n    },\n    {\n      \"card_no\": 2,\n      \"card_type\": \"중간 카드\",\n      \"template_name\": \"Instagram post - middle\",\n      \"layout_type\": \"stacked_boxes\",\n      \"cloud_label\": \"\",\n      \"series_title\": \"성수기 CS 인력 운영 문제\",\n      \"title\": \"고정된 인력 운영이\\n만드는 악순환\",\n      \"highlight_text\": \"\",\n      \"subtitle\": \"단순 인력 부족을 넘어선 비효율\",\n      \"body\": \"고정된 인력 운영 방식이 성수기에 비효율을 낳고 고객 이탈을 유발하는 악순환의 근본적인 원인을 설명합니다.\",\n      \"items\": [\n        {\n          \"item_title\": \"채용·교육 비용\",\n          \"item_body\": \"급한 충원 비용, 높은 이직률 부담\"\n        },\n        {\n          \"item_title\": \"기존 인력 소진\",\n          \"item_body\": \"업무 과중으로 서비스 품질 하락\"\n        },\n        {\n          \"item_title\": \"비수기 인력 과잉\",\n          \"item_body\": \"줄어든 문의에 인력 운영 비효율\"\n        }\n      ],\n      \"cta\": \"\",\n      \"design_point\": \"\"\n    },\n    {\n      \"card_no\": 3,\n      \"card_type\": \"중간 카드\",\n      \"template_name\": \"Instagram post - middle\",\n      \"layout_type\": \"keyword_boxes\",\n      \"cloud_label\": \"\",\n      \"series_title\": \"성수기 CS 인력 운영 문제\",\n      \"title\": \"인력 공백이 만드는\\n매출 손실 시그널\",\n      \"highlight_text\": \"\",\n      \"subtitle\": \"고객 이탈을 알리는 3가지 현상\",\n      \"body\": \"CS 인력 공백이 구체적으로 어떤 운영상 문제를 일으키고, 이것이 어떻게 매출 손실로 이어지는지 고객 경험 관점에서 제시합니다.\",\n      \"items\": [\n        {\n          \"item_title\": \"긴 대기 시간\",\n          \"item_body\": \"문의 포기, 잠재 고객 이탈 전환\"\n        },\n        {\n          \"item_title\": \"불확실한 안내\",\n          \"item_body\": \"신뢰 하락, 재구매 의사 감소\"\n        },\n        {\n          \"item_title\": \"중요 VOC 누락\",\n          \"item_body\": \"단순 문의에 가려진 핵심 피드백\"\n        }\n      ],\n      \"cta\": \"\",\n      \"design_point\": \"\"\n    },\n    {\n      \"card_no\": 4,\n      \"card_type\": \"중간 카드\",\n      \"template_name\": \"Instagram post - middle\",\n      \"layout_type\": \"stacked_boxes\",\n      \"cloud_label\": \"\",\n      \"series_title\": \"성수기 CS 인력 운영 문제\",\n      \"title\": \"성수기 CS,\\n유연한 운영 전략\",\n      \"highlight_text\": \"\",\n      \"subtitle\": \"필요한 만큼만, 즉시 전문성 확보\",\n      \"body\": \"성수기 인력 공백 문제를 극복하고 매출 기회로 전환하기 위한 유연하고 전문적인 CS 운영 전략의 핵심 포인트를 제시합니다.\",\n      \"items\": [\n        {\n          \"item_title\": \"문의량에 맞게\",\n          \"item_body\": \"시즌별 유연한 인력 규모 조절\"\n        },\n        {\n          \"item_title\": \"숙련된 전문가\",\n          \"item_body\": \"즉시 투입 가능한 전문 CS 인력\"\n        },\n        {\n          \"item_title\": \"핵심 VOC 집중\",\n          \"item_body\": \"서비스 품질 유지 및 고객 경험 향상\"\n        }\n      ],\n      \"cta\": \"\",\n      \"design_point\": \"\"\n    },\n    {\n      \"card_no\": 5,\n      \"card_type\": \"CTA 카드\",\n      \"template_name\": \"Instagram post - CTA\",\n      \"layout_type\": \"cta\",\n      \"cloud_label\": \"\",\n      \"series_title\": \"\",\n      \"title\": \"우리 기업에 딱 맞는\\n성수기 CS 전략은?\",\n      \"highlight_text\": \"\",\n      \"subtitle\": \"CS쉐어링이 함께 고민합니다\",\n      \"body\": \"우리 기업에 맞는 성수기 CS 운영 방식과 전략을 점검해 볼 것을 제안하며, CS쉐어링의 도움을 받을 수 있음을 안내합니다.\",\n      \"items\": [],\n      \"cta\": \"CS쉐어링 서비스 확인하기\",\n      \"design_point\": \"\"\n    }\n  ],\n  \"caption\": \"💡 성수기 CS, '인력 공백'이 단순한 문제가 아닙니다.\\n\\n많은 기업들이 성수기 고객 문의 폭증에 대비하지만, 고정된 CS 인력 운영의 한계에 부딪히곤 합니다. 갑작스러운 인력 충원의 어려움, 기존 인력의 업무 과중, 그리고 비수기 인력 비효율은 기업의 잠재적 매출 손실로 이어지는 악순환을 만듭니다.\\n\\n📌 고객이 길어진 대기 시간에 이탈하고, 불확실한 안내에 재구매를 망설이며, 중요한 VOC가 단순 문의에 묻히는 상황. 이 모든 것이 인력 공백이 만들어내는 매출 손실의 명확한 신호입니다. 성수기는 매출을 극대화할 기회이지, CS 문제로 고객을 잃는 위기가 되어서는 안 됩니다.\\n\\n📌 유연한 CS 운영 전략은 필수입니다. 문의량에 맞춰 인력 규모를 조절하고, 숙련된 전문 인력을 즉시 투입할 수 있다면, 고객 이탈을 줄이고 재구매율을 높여 매출 손실을 방지할 수 있습니다. 핵심 VOC에 집중하여 서비스 품질을 유지하는 것이 중요합니다.\\n\\n👉 우리 기업의 성수기 CS 운영, 현재 어떤 지점을 점검해야 할까요? CS쉐어링과 함께 효율적인 CS 운영 방안을 논의해보세요.\",\n  \"hashtags\": [\n    \"#CS쉐어링\",\n    \"#CS대행\",\n    \"#고객센터대행\",\n    \"#성수기CS\",\n    \"#CS인력\",\n    \"#매출손실\",\n    \"#이커머스CS\",\n    \"#CX전략\",\n    \"#고객경험\",\n    \"#운영효율\"\n  ],\n  \"article_body\": \"\",\n  \"image_prompt\": \"\",\n  \"review_result\": {}\n}"
  }
}